deathbycaptcha/__init__.py
deathbycaptcha/deathbycaptcha.py
deathbycaptcha_official-4.6.2.dist-info/LICENSE
deathbycaptcha_official-4.6.2.dist-info/METADATA
deathbycaptcha_official-4.6.2.dist-info/WHEEL
deathbycaptcha_official-4.6.2.dist-info/top_level.txt
deathbycaptcha_official-4.6.2.dist-info/RECORD
