Metadata-Version: 2.2
Name: deathbycaptcha-official
Version: 4.6.2
Summary: Official DeathByCaptcha API Client Library
Home-page: https://github.com/deathbycaptcha/python_client_library
Author: DBC Developers Team
Author-email: deathbycaptcha@protonmail.com
Project-URL: Bug Tracker, https://github.com/deathbycaptcha/python_client_library/issues
Project-URL: repository, https://github.com/deathbycaptcha/python_client_library
Classifier: Programming Language :: Python :: 3
Classifier: License :: OSI Approved :: MIT License
Classifier: Operating System :: OS Independent
Requires-Python: >=3.6
License-File: LICENSE
Requires-Dist: requests>=2.25.1
Requires-Dist: simplejson>=3.17.2
